{
    "version": "4.5.7",
    "flags": {},
    "shapes": [
        {
            "label": "mamoa",
            "points": [
                [
                    583.5234375,
                    440.41406250000006
                ],
                [
                    654.0703125,
                    440.41406250000006
                ],
                [
                    654.0703125,
                    510.96093750000006
                ],
                [
                    583.5234375,
                    510.96093750000006
                ]
            ],
            "group_id": null,
            "shape_type": "polygon",
            "flags": {}
        }
    ],
    "imagePath": "69_1.jpg",
    "imageHeight": 645,
    "imageWidth": 645
}