{
    "version": "4.5.7",
    "flags": {},
    "shapes": [
        {
            "label": "mamoa",
            "points": [
                [
                    449.79375000000005,
                    89.6953125
                ],
                [
                    479.98125000000005,
                    89.6953125
                ],
                [
                    479.98125000000005,
                    119.9296875
                ],
                [
                    449.79375000000005,
                    119.9296875
                ]
            ],
            "group_id": null,
            "shape_type": "polygon",
            "flags": {}
        }
    ],
    "imagePath": "57_1.jpg",
    "imageHeight": 645,
    "imageWidth": 644
}