{
    "version": "4.5.7",
    "flags": {},
    "shapes": [
        [
            {
                "label": "mamoa",
                "points": [
                    [
                        41.256249999999994,
                        229.715625
                    ],
                    [
                        71.44375,
                        229.715625
                    ],
                    [
                        71.44375,
                        259.809375
                    ],
                    [
                        41.256249999999994,
                        259.809375
                    ]
                ],
                "group_id": null,
                "shape_type": "polygon",
                "flags": {}
            }
        ]
    ],
    "imagePath": "22_1_0.json",
    "imageHeight": 642,
    "imageWidth": 644
}