{
    "version": "4.5.7",
    "flags": {},
    "shapes": [
        {
            "label": "mamoa",
            "points": [
                [
                    607.7750000000001,
                    507.58124999999995
                ],
                [
                    644.0,
                    507.58124999999995
                ],
                [
                    644.0,
                    551.71875
                ],
                [
                    607.7750000000001,
                    551.71875
                ]
            ],
            "group_id": null,
            "shape_type": "polygon",
            "flags": {}
        }
    ],
    "imagePath": "34_1_2.jpg",
    "imageHeight": 642,
    "imageWidth": 644
}