{
    "version": "4.5.7",
    "flags": {},
    "shapes": [
        {
            "label": "mamoa",
            "points": [
                [
                    260.01562499999994,
                    519.225
                ],
                [
                    300.32812499999994,
                    519.225
                ],
                [
                    300.32812499999994,
                    559.475
                ],
                [
                    260.01562499999994,
                    559.475
                ]
            ],
            "group_id": null,
            "shape_type": "polygon",
            "flags": {}
        }
    ],
    "imagePath": "53_1_1.jpg",
    "imageHeight": 644,
    "imageWidth": 645
}